flake8_arg_spacing.py
flake8_arg_spacing-1.1.0.dist-info/licenses/LICENSE.txt
flake8_arg_spacing-1.1.0.dist-info/METADATA
flake8_arg_spacing-1.1.0.dist-info/WHEEL
flake8_arg_spacing-1.1.0.dist-info/entry_points.txt
flake8_arg_spacing-1.1.0.dist-info/top_level.txt
flake8_arg_spacing-1.1.0.dist-info/RECORD
