Metadata-Version: 2.4
Name: flake8-arg-spacing
Version: 1.1.0
Summary: Flake8 plugin that checks against poor spacing around the equals sign in function arguments.
License-Expression: MIT
Project-URL: Homepage, https://github.com/adamsol/flake8-arg-spacing
Requires-Python: >=3.9
License-File: LICENSE.txt
Requires-Dist: flake8
Dynamic: license-file
